MANIFEST.in
setup.py
masonite/contrib/rackspace/__init__.py
masonite/contrib/rackspace/drivers/UploadRackspaceDriver.py
masonite/contrib/rackspace/drivers/__init__.py
masonite/contrib/rackspace/providers/AzureProvider.py
masonite/contrib/rackspace/providers/__init__.py
masonite_rackspace_driver.egg-info/PKG-INFO
masonite_rackspace_driver.egg-info/SOURCES.txt
masonite_rackspace_driver.egg-info/dependency_links.txt
masonite_rackspace_driver.egg-info/requires.txt
masonite_rackspace_driver.egg-info/top_level.txt