Metadata-Version: 1.0
Name: masonite-rackspace-driver
Version: 0.0.5
Summary: Rackspace upload driver for the Masonite framework
Home-page: https://github.com/josephmancuso/masonite-rackspace-driver
Author: Joseph Mancuso
Author-email: idmann509@gmail.com
License: UNKNOWN
Keywords: python web framework,python3,masonite,rackspace
Platform: UNKNOWN
